docmesh_server/__init__.py
docmesh_server/database.py
docmesh_server/dependencies.py
docmesh_server/main.py
docmesh_server/internals/__init__.py
docmesh_server/internals/admin.py
docmesh_server/internals/collections.py
docmesh_server/internals/embeddings.py
docmesh_server/internals/pdfs.py
docmesh_server/internals/venues.py
docmesh_server/routers/__init__.py
docmesh_server/routers/agents.py
docmesh_server/routers/entities.py
docmesh_server/routers/graphs.py
docmesh_server/routers/papers.py
docmesh_server/routers/posters.py
docmesh_server/routers/sessions.py
docmesh_server-0.0.20.dist-info/WHEEL
docmesh_server-0.0.20.dist-info/METADATA
docmesh_server-0.0.20.dist-info/RECORD
