Metadata-Version: 2.3
Name: docmesh_server
Version: 0.0.20
Summary: Server of docmesh.
Author-email: Zhengkai Yang <kyle.yang1995@gmail.com>
Requires-Python: >=3.8
Classifier: Programming Language :: Python :: 3.8
Classifier: Programming Language :: Python :: 3.9
Classifier: Programming Language :: Python :: 3.10
Classifier: Operating System :: OS Independent
Requires-Dist: docmesh-core>=0.0.16
Requires-Dist: docmesh-agent>=0.0.13
Requires-Dist: fastapi==0.111.0
Requires-Dist: uvicorn==0.29.0
Requires-Dist: gunicorn==19.3.0
